LICENSE
MANIFEST.in
README.rst
requirements.txt
setup.py
examples/basic.py
examples/interrogator_basic.yaml
examples/interrogator_with_hooks.yaml
examples/with_hooks.py
interrogator/__init__.py
interrogator/_version.py
interrogator.egg-info/PKG-INFO
interrogator.egg-info/SOURCES.txt
interrogator.egg-info/dependency_links.txt
interrogator.egg-info/requires.txt
interrogator.egg-info/top_level.txt
interrogator/context/__init__.py
interrogator/context/context.py
interrogator/exception/__init__.py
interrogator/io/__init__.py
interrogator/question/__init__.py
interrogator/question/question.py