Metadata-Version: 1.0
Name: interrogator
Version: 0.4.0
Summary: Populating and asking a nested series of questions populated by a YAML config file.
Home-page: https://github.com/jackmaney/interrogator.git
Author: Jack Maney
Author-email: jackmaney@gmail.com
License: MIT
Platform: UNKNOWN
